{"cameraMode":{"drawMode":0,"name":"Shaded","section":"Shading Mode"},"sceneLighting":false,"audioPlay":false,"sceneViewState":{"m_AlwaysRefresh":false,"showFog":true,"showSkybox":false,"showFlares":true,"showImageEffects":true,"showParticleSystems":true,"showVisualEffectGraphs":true,"m_FxEnabled":true},"in2DMode":false,"pivot":{"x":594.2354125976563,"y":206.4833984375,"z":207.54745483398438},"rotation":{"x":0.10655586421489716,"y":0.15004171431064607,"z":-0.01626759208738804,"w":0.9827854633331299},"size":235.97592163085938,"orthographic":false}